Metadata-Version: 2.1
Name: mkdocs-ja-ruby
Version: 0.0.2
Summary: Just for fun. A ruby plugin for mkdocs
Home-page: https://ashitemaru.github.io
Author: Ashitemaru
Author-email: ashitemaru.holder@gmail.com
License: UNKNOWN
Platform: UNKNOWN
